pascal/__init__.py
pascal/annotation_fabric.py
pascal/draw_objects.py
pascal/exceptions.py
pascal/format_convertor.py
pascal/pascal_annotation.py
pascal/protocol_implementations.py
pascal/protocols.py
pascal/utils.py
pascal/fonts/arialmt.ttf
pascal_voc-2.1.12.data/data/pascal/arialmt.ttf
pascal_voc-2.1.12.dist-info/LICENSE
pascal_voc-2.1.12.dist-info/METADATA
pascal_voc-2.1.12.dist-info/WHEEL
pascal_voc-2.1.12.dist-info/top_level.txt
pascal_voc-2.1.12.dist-info/RECORD
