Metadata-Version: 2.2
Name: pascal_voc
Version: 2.1.12
Summary: Tool to work with annotation formats
Author: Alexander Barmin
Author-email: Alexander Barmin <barmin1@mail.ru>
License: MIT License
Project-URL: Homepage, https://github.com/Alek-dr/PascalVOC
Project-URL: Issues, https://github.com/Alek-dr/PascalVOC/issues
Classifier: Programming Language :: Python :: 3
Classifier: License :: OSI Approved :: MIT License
Classifier: Operating System :: OS Independent
Requires-Python: >=3.6
License-File: LICENSE
Requires-Dist: Pillow>=8.1.0
Requires-Dist: transliterate>=1.10.2
Requires-Dist: xmlobj>=1.2.2
Requires-Dist: typing_extensions>=4.1.0
Dynamic: author
Dynamic: requires-python
